sf_git/__init__.py
sf_git/cache.py
sf_git/cli.py
sf_git/commands.py
sf_git/config.py
sf_git/git_utils.py
sf_git/models.py
sf_git/rest_utils.py
sf_git/sf_git.conf
sf_git/snowsight_auth.py
sf_git/worksheets_utils.py
sf_git-1.4.2.dist-info/LICENSE
sf_git-1.4.2.dist-info/METADATA
sf_git-1.4.2.dist-info/WHEEL
sf_git-1.4.2.dist-info/entry_points.txt
sf_git-1.4.2.dist-info/top_level.txt
sf_git-1.4.2.dist-info/RECORD
