Metadata-Version: 2.1
Name: sf_git
Version: 1.4.2
Summary: Python package to manipulate Snowsight worksheets
Home-page: https://github.com/tdambrin/sf_git
Author: Thomas Dambrin
Author-email: thomas.dambrin@gmail.com
License: MIT
Keywords: python,snowflake,git
Classifier: Intended Audience :: Developers
Classifier: Programming Language :: Python :: 3
Classifier: Operating System :: MacOS :: MacOS X
Classifier: Operating System :: Unix
Classifier: Operating System :: Microsoft :: Windows
License-File: LICENSE
Requires-Dist: pip >=21.3.1
Requires-Dist: setuptools >=56
Requires-Dist: pandas
Requires-Dist: coverage
Requires-Dist: python-dotenv
Requires-Dist: click ==7.1.2
Requires-Dist: deepdiff
Requires-Dist: gitpython >=3.1
Requires-Dist: requests
Requires-Dist: urllib3
